kproxy/__init__.py
kproxy/proxy.py
kproxy-0.0.1.dist-info/LICENSE
kproxy-0.0.1.dist-info/METADATA
kproxy-0.0.1.dist-info/WHEEL
kproxy-0.0.1.dist-info/top_level.txt
kproxy-0.0.1.dist-info/RECORD
